async_youtube_search/__init__.py
async_youtube_search-2.dist-info/METADATA
async_youtube_search-2.dist-info/WHEEL
async_youtube_search-2.dist-info/top_level.txt
async_youtube_search-2.dist-info/RECORD
