Metadata-Version: 2.1
Name: async-youtube-search
Version: 2
Summary: Perform YouTube video searches without the API
Home-page: https://github.com/rafkix/async-youtube-search
Author: Rafkix
Author-email: rafkixuz@gmail.com
License: MIT
Classifier: License :: OSI Approved :: MIT License
Classifier: Programming Language :: Python :: 3
Classifier: Programming Language :: Python :: 3.11
Classifier: Programming Language :: Python :: 3.13
Requires-Dist: requests
